django_firebase_cache/__init__.py
django_firebase_cache/firestore.py
django_firebase_cache/realtime_database.py
django_firebase_cache-19.6.2.dist-info/LICENSE
django_firebase_cache-19.6.2.dist-info/METADATA
django_firebase_cache-19.6.2.dist-info/WHEEL
django_firebase_cache-19.6.2.dist-info/top_level.txt
django_firebase_cache-19.6.2.dist-info/RECORD
