Metadata-Version: 2.1
Name: django-firebase-cache
Version: 19.6.2
Summary: Firebase cache for Django
Home-page: http://github.com/christippett/django-firebase-cache/
Author: Chris Tippett
Author-email: c.tippett@gmail.com
License: MIT
Platform: UNKNOWN
Classifier: Programming Language :: Python
Classifier: Programming Language :: Python :: 3.6
Classifier: Programming Language :: Python :: 3.7
Classifier: License :: OSI Approved :: MIT License
Classifier: Operating System :: OS Independent
Classifier: Topic :: Software Development :: Libraries
Classifier: Topic :: Utilities
Classifier: Environment :: Web Environment
Classifier: Framework :: Django
Classifier: Framework :: Django :: 1.11
Classifier: Framework :: Django :: 2.0
Classifier: Framework :: Django :: 2.1
Classifier: Framework :: Django :: 2.2
Requires-Dist: google-cloud-firestore
Requires-Dist: firebase-admin
